Workbook

Sheet CorST
A1: Слово | B1: Частота-CorST | C1: IPM-CorST | D1: Ранг-CorST | E1: Номер строки, на которой слово стоит в RLC | F1: IPM-RLC
A2: в | B2: 35889 | C2: 11520.564 | D2: =RANK(B2,B:B) -> 1 | E2: =MATCH(A2,RLC!A:A,0) -> 8126 | F2: {=INDEX(RLC!C:C,E2)} -> 37993.234 | G2: {=INDEX(RLC!D:D,F2)}
A3: и | B3: 31435 | C3: 10090.806 | D3: =RANK(B3,B:B) -> 2 | E3: =MATCH(A3,RLC!A:A,0) -> 8125 | F3: {=INDEX(RLC!C:C,E3)} -> 38334.702
A4: на | B4: 13212 | C4: 4241.1239 | D4: =RANK(B4,B:B) -> 3 | E4: =MATCH(A4,RLC!A:A,0) -> 8124 | F4: {=INDEX(RLC!C:C,E4)} -> 13265.412
A5: не | B5: 11811 | C5: 3791.3953 | D5: =RANK(B5,B:B) -> 4 | E5: =MATCH(A5,RLC!A:A,0) -> 8123 | F5: {=INDEX(RLC!C:C,E5)} -> 12860.168
A6: с | B6: 11363 | C6: 3647.5848 | D6: =RANK(B6,B:B) -> 5 | E6: =MATCH(A6,RLC!A:A,0) -> 8122 | F6: {=INDEX(RLC!C:C,E6)} -> 9178.432
A7: что | B7: 10265 | C7: 3295.1208 | D7: =RANK(B7,B:B) -> 6 | E7: =MATCH(A7,RLC!A:A,0) -> 8121 | F7: {=INDEX(RLC!C:C,E7)} -> 16305.402
A8: как | B8: 7396 | C8: 2374.1562 | D8: =RANK(B8,B:B) -> 7 | E8: =MATCH(A8,RLC!A:A,0) -> 8120 | F8: {=INDEX(RLC!C:C,E8)} -> 8273.6097
A9: к | B9: 6790 | C9: 2179.6269 | D9: =RANK(B9,B:B) -> 8 | E9: =MATCH(A9,RLC!A:A,0) -> 8119 | F9: {=INDEX(RLC!C:C,E9)} -> 4742.0127
A10: а | B10: 5924 | C10: 1901.6362 | D10: =RANK(B10,B:B) -> 9 | E10: =MATCH(A10,RLC!A:A,0) -> 8118 | F10: {=INDEX(RLC!C:C,E10)} -> 3449.2197
A11: для | B11: 5652 | C11: 1814.3227 | D11: =RANK(B11,B:B) -> 10 | E11: =MATCH(A11,RLC!A:A,0) -> 8117 | F11: {=INDEX(RLC!C:C,E11)} -> 5009.0748
A12: по | B12: 5634 | C12: 1808.5447 | D12: =RANK(B12,B:B) -> 11 | E12: =MATCH(A12,RLC!A:A,0) -> 8116 | F12: {=INDEX(RLC!C:C,E12)} -> 4641.034
A13: о | B13: 4912 | C13: 1576.7787 | D13: =RANK(B13,B:B) -> 12 | E13: =MATCH(A13,RLC!A:A,0) -> 8115 | F13: {=INDEX(RLC!C:C,E13)} -> 5022.3615
A14: из | B14: 4365 | C14: 1401.1887 | D14: =RANK(B14,B:B) -> 13 | E14: =MATCH(A14,RLC!A:A,0) -> 8114 | F14: {=INDEX(RLC!C:C,E14)} -> 4432.4333
... A1349: форм | B1349: 92 | C1349: 29.532501 | D1349: =RANK(B1349,B:B) -> 1326 | E1349: =MATCH(A1349,RLC!A:A,0) -> 6925 | F1349: {=INDEX(RLC!C:C,E1349)} -> 21.258673
A1350: школе | B1350: 92 | C1350: 29.532501 | D1350: =RANK(B1350,B:B) -> 1326 | E1350: =MATCH(A1350,RLC!A:A,0) -> 6924 | F1350: {=INDEX(RLC!C:C,E1350)} -> 259.09008 | G1350: =C1350>E1350 -> FALSE
A1351: элементов | B1351: 92 | C1351: 29.532501 | D1351: =RANK(B1351,B:B) -> 1326 | E1351: =MATCH(A1351,RLC!A:A,0) -> 6923 | F1351: {=INDEX(RLC!C:C,E1351)} -> 27.902008
A1352: этими | B1352: 92 | C1352: 29.532501 | D1352: =RANK(B1352,B:B) -> 1326 | E1352: =MATCH(A1352,RLC!A:A,0) -> 6922 | F1352: {=INDEX(RLC!C:C,E1352)} -> 77.062689
A1353: артикля | B1353: 91 | C1353: 29.211495 | D1353: =RANK(B1353,B:B) -> 1352 | E1353: =MATCH(A1353,RLC!A:A,0) -> #N/A | F1353: {=INDEX(RLC!C:C,E1353)} -> #N/A
A1354: всему | B1354: 91 | C1354: 29.211495 | D1354: =RANK(B1354,B:B) -> 1352 | E1354: =MATCH(A1354,RLC!A:A,0) -> 6921 | F1354: {=INDEX(RLC!C:C,E1354)} -> 144.82471
A1355: выполнения | B1355: 91 | C1355: 29.211495 | D1355: =RANK(B1355,B:B) -> 1352 | E1355: =MATCH(A1355,RLC!A:A,0) -> #N/A | F1355: {=INDEX(RLC!C:C,E1355)} -> #N/A
A1356: достоевский | B1356: 91 | C1356: 29.211495 | D1356: =RANK(B1356,B:B) -> 1352 | E1356: =MATCH(A1356,RLC!A:A,0) -> #N/A | F1356: {=INDEX(RLC!C:C,E1356)} -> #N/A
A1357: менеджмента | B1357: 91 | C1357: 29.211495 | D1357: =RANK(B1357,B:B) -> 1352 | E1357: =MATCH(A1357,RLC!A:A,0) -> 6920 | F1357: {=INDEX(RLC!C:C,E1357)} -> 39.860012
A1358: наша | B1358: 91 | C1358: 29.211495 | D1358: =RANK(B1358,B:B) -> 1352 | E1358: =MATCH(A1358,RLC!A:A,0) -> 6919 | F1358: {=INDEX(RLC!C:C,E1358)} -> 193.98539
A1359: поднятая | B1359: 91 | C1359: 29.211495 | D1359: =RANK(B1359,B:B) -> 1352 | E1359: =MATCH(A1359,RLC!A:A,0) -> #N/A | F1359: {=INDEX(RLC!C:C,E1359)} -> #N/A
A1360: постепенно | B1360: 91 | C1360: 29.211495 | D1360: =RANK(B1360,B:B) -> 1352 | E1360: =MATCH(A1360,RLC!A:A,0) -> 6918 | F1360: {=INDEX(RLC!C:C,E1360)} -> 46.503347
A1361: рублей | B1361: 91 | C1361: 29.211495 | D1361: =RANK(B1361,B:B) -> 1352 | E1361: =MATCH(A1361,RLC!A:A,0) -> 6917 | F1361: {=INDEX(RLC!C:C,E1361)} -> 67.76202
A1362: сегодняшний | B1362: 91 | C1362: 29.211495 | D1362: =RANK(B1362,B:B) -> 1352 | E1362: =MATCH(A1362,RLC!A:A,0) -> 6916 | F1362: {=INDEX(RLC!C:C,E1362)} -> 62.447352
... A1716: чехов | B1716: 73 | C1716: 23.433397 | D1716: =RANK(B1716,B:B) -> 1684 | E1716: =MATCH(A1716,RLC!A:A,0) -> #N/A | F1716: {=INDEX(RLC!C:C,E1716)} -> #N/A
A1717: шапочка | B1717: 73 | C1717: 23.433397 | D1717: =RANK(B1717,B:B) -> 1684 | E1717: =MATCH(A1717,RLC!A:A,0) -> 6655 | F1717: {=INDEX(RLC!C:C,E1717)} -> 34.545343 | G1717: =C1717>E1717 -> FALSE
A1718: широко | B1718: 73 | C1718: 23.433397 | D1718: =RANK(B1718,B:B) -> 1684 | E1718: =MATCH(A1718,RLC!A:A,0) -> 6654 | F1718: {=INDEX(RLC!C:C,E1718)} -> 73.076688 | G1718: =C1718>E1718 -> FALSE
A1719: эмоций | B1719: 73 | C1719: 23.433397 | D1719: =RANK(B1719,B:B) -> 1684 | E1719: =MATCH(A1719,RLC!A:A,0) -> 6653 | F1719: {=INDEX(RLC!C:C,E1719)} -> 15.944005
A1720: большие | B1720: 72 | C1720: 23.112392 | D1720: =RANK(B1720,B:B) -> 1719 | E1720: =MATCH(A1720,RLC!A:A,0) -> 6652 | F1720: {=INDEX(RLC!C:C,E1720)} -> 128.8807
A1721: большого | B1721: 72 | C1721: 23.112392 | D1721: =RANK(B1721,B:B) -> 1719 | E1721: =MATCH(A1721,RLC!A:A,0) -> 6651 | F1721: {=INDEX(RLC!C:C,E1721)} -> 42.517346
A1722: ведет | B1722: 72 | C1722: 23.112392 | D1722: =RANK(B1722,B:B) -> 1719 | E1722: =MATCH(A1722,RLC!A:A,0) -> 6650 | F1722: {=INDEX(RLC!C:C,E1722)} -> 31.888009
A1723: вниз | B1723: 72 | C1723: 23.112392 | D1723: =RANK(B1723,B:B) -> 1719 | E1723: =MATCH(A1723,RLC!A:A,0) -> 6649 | F1723: {=INDEX(RLC!C:C,E1723)} -> 39.860012
A1724: вузов | B1724: 72 | C1724: 23.112392 | D1724: =RANK(B1724,B:B) -> 1719 | E1724: =MATCH(A1724,RLC!A:A,0) -> 6648 | F1724: {=INDEX(RLC!C:C,E1724)} -> 17.272672
A1725: выражений | B1725: 72 | C1725: 23.112392 | D1725: =RANK(B1725,B:B) -> 1719 | E1725: =MATCH(A1725,RLC!A:A,0) -> 6647 | F1725: {=INDEX(RLC!C:C,E1725)} -> 29.230675
A1726: гражданским | B1726: 72 | C1726: 23.112392 | D1726: =RANK(B1726,B:B) -> 1719 | E1726: =MATCH(A1726,RLC!A:A,0) -> #N/A | F1726: {=INDEX(RLC!C:C,E1726)} -> #N/A
A1727: изучить | B1727: 72 | C1727: 23.112392 | D1727: =RANK(B1727,B:B) -> 1719 | E1727: =MATCH(A1727,RLC!A:A,0) -> 6646 | F1727: {=INDEX(RLC!C:C,E1727)} -> 25.244674
A1728: ин | B1728: 72 | C1728: 23.112392 | D1728: =RANK(B1728,B:B) -> 1719 | E1728: =MATCH(A1728,RLC!A:A,0) -> #N/A | F1728: {=INDEX(RLC!C:C,E1728)} -> #N/A
A1729: интернета | B1729: 72 | C1729: 23.112392 | D1729: =RANK(B1729,B:B) -> 1719 | E1729: =MATCH(A1729,RLC!A:A,0) -> 6645 | F1729: {=INDEX(RLC!C:C,E1729)} -> 38.531345
A1730: когнитивных | B1730: 72 | C1730: 23.112392 | D1730: =RANK(B1730,B:B) -> 1719 | E1730: =MATCH(A1730,RLC!A:A,0) -> #N/A | F1730: {=INDEX(RLC!C:C,E1730)} -> #N/A
... A2090: чтение | B2090: 61 | C2090: 19.581332 | D2090: =RANK(B2090,B:B) -> 2063 | E2090: =MATCH(A2090,RLC!A:A,0) -> 6394 | F2090: {=INDEX(RLC!C:C,E2090)} -> 43.846013
A2091: школы | B2091: 61 | C2091: 19.581332 | D2091: =RANK(B2091,B:B) -> 2063 | E2091: =MATCH(A2091,RLC!A:A,0) -> 6393 | F2091: {=INDEX(RLC!C:C,E2091)} -> 197.97139 | G2091: =C2091>E2091 -> FALSE
A2092: больших | B2092: 60 | C2092: 19.260326 | D2092: =RANK(B2092,B:B) -> 2091 | E2092: =MATCH(A2092,RLC!A:A,0) -> 6392 | F2092: {=INDEX(RLC!C:C,E2092)} -> 102.30736
A2093: будем | B2093: 60 | C2093: 19.260326 | D2093: =RANK(B2093,B:B) -> 2091 | E2093: =MATCH(A2093,RLC!A:A,0) -> 6391 | F2093: {=INDEX(RLC!C:C,E2093)} -> 100.9787
A2094: вариативность | B2094: 60 | C2094: 19.260326 | D2094: =RANK(B2094,B:B) -> 2091 | E2094: =MATCH(A2094,RLC!A:A,0) -> #N/A | F2094: {=INDEX(RLC!C:C,E2094)} -> #N/A
A2095: возмещения | B2095: 60 | C2095: 19.260326 | D2095: =RANK(B2095,B:B) -> 2091 | E2095: =MATCH(A2095,RLC!A:A,0) -> #N/A | F2095: {=INDEX(RLC!C:C,E2095)} -> #N/A
A2096: возможностей | B2096: 60 | C2096: 19.260326 | D2096: =RANK(B2096,B:B) -> 2091 | E2096: =MATCH(A2096,RLC!A:A,0) -> 6390 | F2096: {=INDEX(RLC!C:C,E2096)} -> 39.860012
A2097: выяснить | B2097: 60 | C2097: 19.260326 | D2097: =RANK(B2097,B:B) -> 2091 | E2097: =MATCH(A2097,RLC!A:A,0) -> 6389 | F2097: {=INDEX(RLC!C:C,E2097)} -> 13.286671
A2098: гипотез | B2098: 60 | C2098: 19.260326 | D2098: =RANK(B2098,B:B) -> 2091 | E2098: =MATCH(A2098,RLC!A:A,0) -> #N/A | F2098: {=INDEX(RLC!C:C,E2098)} -> #N/A
A2099: голове | B2099: 60 | C2099: 19.260326 | D2099: =RANK(B2099,B:B) -> 2091 | E2099: =MATCH(A2099,RLC!A:A,0) -> 6388 | F2099: {=INDEX(RLC!C:C,E2099)} -> 53.146682
A2100: гражданском | B2100: 60 | C2100: 19.260326 | D2100: =RANK(B2100,B:B) -> 2091 | E2100: =MATCH(A2100,RLC!A:A,0) -> #N/A | F2100: {=INDEX(RLC!C:C,E2100)} -> #N/A
A2101: дается | B2101: 60 | C2101: 19.260326 | D2101: =RANK(B2101,B:B) -> 2091 | E2101: =MATCH(A2101,RLC!A:A,0) -> 6387 | F2101: {=INDEX(RLC!C:C,E2101)} -> 26.573341
A2102: дальнейшего | B2102: 60 | C2102: 19.260326 | D2102: =RANK(B2102,B:B) -> 2091 | E2102: =MATCH(A2102,RLC!A:A,0) -> #N/A | F2102: {=INDEX(RLC!C:C,E2102)} -> #N/A
A2103: другая | B2103: 60 | C2103: 19.260326 | D2103: =RANK(B2103,B:B) -> 2091 | E2103: =MATCH(A2103,RLC!A:A,0) -> 6386 | F2103: {=INDEX(RLC!C:C,E2103)} -> 96.992695
... A2510: фоне | B2510: 50 | C2510: 16.050272 | D2510: =RANK(B2510,B:B) -> 2456 | E2510: =MATCH(A2510,RLC!A:A,0) -> #N/A | F2510: {=INDEX(RLC!C:C,E2510)} -> #N/A
A2511: широкий | B2511: 50 | C2511: 16.050272 | D2511: =RANK(B2511,B:B) -> 2456 | E2511: =MATCH(A2511,RLC!A:A,0) -> 6130 | F2511: {=INDEX(RLC!C:C,E2511)} -> 15.944005 | G2511: =C2511>E2511 -> FALSE
A2512: адресован | B2512: 49 | C2512: 15.729267 | D2512: =RANK(B2512,B:B) -> 2511 | E2512: =MATCH(A2512,RLC!A:A,0) -> #N/A | F2512: {=INDEX(RLC!C:C,E2512)} -> #N/A
A2513: база | B2513: 49 | C2513: 15.729267 | D2513: =RANK(B2513,B:B) -> 2511 | E2513: =MATCH(A2513,RLC!A:A,0) -> #N/A | F2513: {=INDEX(RLC!C:C,E2513)} -> #N/A
A2514: вариативности | B2514: 49 | C2514: 15.729267 | D2514: =RANK(B2514,B:B) -> 2511 | E2514: =MATCH(A2514,RLC!A:A,0) -> #N/A | F2514: {=INDEX(RLC!C:C,E2514)} -> #N/A
A2515: введения | B2515: 49 | C2515: 15.729267 | D2515: =RANK(B2515,B:B) -> 2511 | E2515: =MATCH(A2515,RLC!A:A,0) -> 6129 | F2515: {=INDEX(RLC!C:C,E2515)} -> 13.286671
A2516: видел | B2516: 49 | C2516: 15.729267 | D2516: =RANK(B2516,B:B) -> 2511 | E2516: =MATCH(A2516,RLC!A:A,0) -> 6128 | F2516: {=INDEX(RLC!C:C,E2516)} -> 59.790017
A2517: высокий | B2517: 49 | C2517: 15.729267 | D2517: =RANK(B2517,B:B) -> 2511 | E2517: =MATCH(A2517,RLC!A:A,0) -> 6127 | F2517: {=INDEX(RLC!C:C,E2517)} -> 53.146682
A2518: выходит | B2518: 49 | C2518: 15.729267 | D2518: =RANK(B2518,B:B) -> 2511 | E2518: =MATCH(A2518,RLC!A:A,0) -> 6126 | F2518: {=INDEX(RLC!C:C,E2518)} -> 30.559342
A2519: герои | B2519: 49 | C2519: 15.729267 | D2519: =RANK(B2519,B:B) -> 2511 | E2519: =MATCH(A2519,RLC!A:A,0) -> 6125 | F2519: {=INDEX(RLC!C:C,E2519)} -> 45.17468
A2520: глагольных | B2520: 49 | C2520: 15.729267 | D2520: =RANK(B2520,B:B) -> 2511 | E2520: =MATCH(A2520,RLC!A:A,0) -> #N/A | F2520: {=INDEX(RLC!C:C,E2520)} -> #N/A
A2521: гпк | B2521: 49 | C2521: 15.729267 | D2521: =RANK(B2521,B:B) -> 2511 | E2521: =MATCH(A2521,RLC!A:A,0) -> #N/A | F2521: {=INDEX(RLC!C:C,E2521)} -> #N/A
A2522: егэ | B2522: 49 | C2522: 15.729267 | D2522: =RANK(B2522,B:B) -> 2511 | E2522: =MATCH(A2522,RLC!A:A,0) -> 6124 | F2522: {=INDEX(RLC!C:C,E2522)} -> 37.202678
A2523: единственный | B2523: 49 | C2523: 15.729267 | D2523: =RANK(B2523,B:B) -> 2511 | E2523: =MATCH(A2523,RLC!A:A,0) -> 6123 | F2523: {=INDEX(RLC!C:C,E2523)} -> 61.118685
... A2664: человеке | B2664: 47 | C2664: 15.087256 | D2664: =RANK(B2664,B:B) -> 2608 | E2664: =MATCH(A2664,RLC!A:A,0) -> 6032 | F2664: {=INDEX(RLC!C:C,E2664)} -> 45.17468
A2665: шаг | B2665: 47 | C2665: 15.087256 | D2665: =RANK(B2665,B:B) -> 2608 | E2665: =MATCH(A2665,RLC!A:A,0) -> 6031 | F2665: {=INDEX(RLC!C:C,E2665)} -> 42.517346 | G2665: =C2665>E2665 -> FALSE
A2666: авторских | B2666: 46 | C2666: 14.76625 | D2666: =RANK(B2666,B:B) -> 2665 | E2666: =MATCH(A2666,RLC!A:A,0) -> #N/A | F2666: {=INDEX(RLC!C:C,E2666)} -> #N/A
A2667: будь | B2667: 46 | C2667: 14.76625 | D2667: =RANK(B2667,B:B) -> 2665 | E2667: =MATCH(A2667,RLC!A:A,0) -> 6030 | F2667: {=INDEX(RLC!C:C,E2667)} -> 34.545343
A2668: бытия | B2668: 46 | C2668: 14.76625 | D2668: =RANK(B2668,B:B) -> 2665 | E2668: =MATCH(A2668,RLC!A:A,0) -> #N/A | F2668: {=INDEX(RLC!C:C,E2668)} -> #N/A
A2669: вводит | B2669: 46 | C2669: 14.76625 | D2669: =RANK(B2669,B:B) -> 2665 | E2669: =MATCH(A2669,RLC!A:A,0) -> #N/A | F2669: {=INDEX(RLC!C:C,E2669)} -> #N/A
A2670: вещь | B2670: 46 | C2670: 14.76625 | D2670: =RANK(B2670,B:B) -> 2665 | E2670: =MATCH(A2670,RLC!A:A,0) -> 6029 | F2670: {=INDEX(RLC!C:C,E2670)} -> 42.517346
A2671: взаимодействии | B2671: 46 | C2671: 14.76625 | D2671: =RANK(B2671,B:B) -> 2665 | E2671: =MATCH(A2671,RLC!A:A,0) -> #N/A | F2671: {=INDEX(RLC!C:C,E2671)} -> #N/A
A2672: выборки | B2672: 46 | C2672: 14.76625 | D2672: =RANK(B2672,B:B) -> 2665 | E2672: =MATCH(A2672,RLC!A:A,0) -> #N/A | F2672: {=INDEX(RLC!C:C,E2672)} -> #N/A
A2673: выделены | B2673: 46 | C2673: 14.76625 | D2673: =RANK(B2673,B:B) -> 2665 | E2673: =MATCH(A2673,RLC!A:A,0) -> #N/A | F2673: {=INDEX(RLC!C:C,E2673)} -> #N/A
A2674: гипотезу | B2674: 46 | C2674: 14.76625 | D2674: =RANK(B2674,B:B) -> 2665 | E2674: =MATCH(A2674,RLC!A:A,0) -> #N/A | F2674: {=INDEX(RLC!C:C,E2674)} -> #N/A
A2675: государств | B2675: 46 | C2675: 14.76625 | D2675: =RANK(B2675,B:B) -> 2665 | E2675: =MATCH(A2675,RLC!A:A,0) -> 6028 | F2675: {=INDEX(RLC!C:C,E2675)} -> 111.60803
A2676: доме | B2676: 46 | C2676: 14.76625 | D2676: =RANK(B2676,B:B) -> 2665 | E2676: =MATCH(A2676,RLC!A:A,0) -> 6027 | F2676: {=INDEX(RLC!C:C,E2676)} -> 120.9087
A2677: думать | B2677: 46 | C2677: 14.76625 | D2677: =RANK(B2677,B:B) -> 2665 | E2677: =MATCH(A2677,RLC!A:A,0) -> 6026 | F2677: {=INDEX(RLC!C:C,E2677)} -> 147.48204
... A2830: ценностей | B2830: 44 | C2830: 14.124239 | D2830: =RANK(B2830,B:B) -> 2779 | E2830: =MATCH(A2830,RLC!A:A,0) -> 5932 | F2830: {=INDEX(RLC!C:C,E2830)} -> 61.118685
A2831: широкого | B2831: 44 | C2831: 14.124239 | D2831: =RANK(B2831,B:B) -> 2779 | E2831: =MATCH(A2831,RLC!A:A,0) -> 5931 | F2831: {=INDEX(RLC!C:C,E2831)} -> 21.258673 | G2831: =C2831>E2831 -> FALSE
A2832: широкой | B2832: 44 | C2832: 14.124239 | D2832: =RANK(B2832,B:B) -> 2779 | E2832: =MATCH(A2832,RLC!A:A,0) -> 5930 | F2832: {=INDEX(RLC!C:C,E2832)} -> 58.46135 | G2832: =C2832>E2832 -> FALSE
A2833: экономиста | B2833: 44 | C2833: 14.124239 | D2833: =RANK(B2833,B:B) -> 2779 | E2833: =MATCH(A2833,RLC!A:A,0) -> #N/A | F2833: {=INDEX(RLC!C:C,E2833)} -> #N/A
A2834: экономического | B2834: 44 | C2834: 14.124239 | D2834: =RANK(B2834,B:B) -> 2779 | E2834: =MATCH(A2834,RLC!A:A,0) -> 5929 | F2834: {=INDEX(RLC!C:C,E2834)} -> 120.9087
A2835: эксперта | B2835: 44 | C2835: 14.124239 | D2835: =RANK(B2835,B:B) -> 2779 | E2835: =MATCH(A2835,RLC!A:A,0) -> #N/A | F2835: {=INDEX(RLC!C:C,E2835)} -> #N/A
A2836: января | B2836: 44 | C2836: 14.124239 | D2836: =RANK(B2836,B:B) -> 2779 | E2836: =MATCH(A2836,RLC!A:A,0) -> 5928 | F2836: {=INDEX(RLC!C:C,E2836)} -> 81.04869
A2837: абстрактное | B2837: 43 | C2837: 13.803234 | D2837: =RANK(B2837,B:B) -> 2836 | E2837: =MATCH(A2837,RLC!A:A,0) -> #N/A | F2837: {=INDEX(RLC!C:C,E2837)} -> #N/A
A2838: автору | B2838: 43 | C2838: 13.803234 | D2838: =RANK(B2838,B:B) -> 2836 | E2838: =MATCH(A2838,RLC!A:A,0) -> 5927 | F2838: {=INDEX(RLC!C:C,E2838)} -> 17.272672
A2839: включая | B2839: 43 | C2839: 13.803234 | D2839: =RANK(B2839,B:B) -> 2836 | E2839: =MATCH(A2839,RLC!A:A,0) -> 5926 | F2839: {=INDEX(RLC!C:C,E2839)} -> 79.720023
A2840: встретить | B2840: 43 | C2840: 13.803234 | D2840: =RANK(B2840,B:B) -> 2836 | E2840: =MATCH(A2840,RLC!A:A,0) -> 5925 | F2840: {=INDEX(RLC!C:C,E2840)} -> 23.916007
A2841: выяснилось | B2841: 43 | C2841: 13.803234 | D2841: =RANK(B2841,B:B) -> 2836 | E2841: =MATCH(A2841,RLC!A:A,0) -> 5924 | F2841: {=INDEX(RLC!C:C,E2841)} -> 15.944005
A2842: грамматика | B2842: 43 | C2842: 13.803234 | D2842: =RANK(B2842,B:B) -> 2836 | E2842: =MATCH(A2842,RLC!A:A,0) -> 5923 | F2842: {=INDEX(RLC!C:C,E2842)} -> 17.272672
A2843: движений | B2843: 43 | C2843: 13.803234 | D2843: =RANK(B2843,B:B) -> 2836 | E2843: =MATCH(A2843,RLC!A:A,0) -> 5922 | F2843: {=INDEX(RLC!C:C,E2843)} -> 25.244674
A2844: доказывает | B2844: 43 | C2844: 13.803234 | D2844: =RANK(B2844,B:B) -> 2836 | E2844: =MATCH(A2844,RLC!A:A,0) -> 5921 | F2844: {=INDEX(RLC!C:C,E2844)} -> 47.832014
...

Sheet RLC
A1: Слово | B1: Частота-RLC | C1: IPM-RLC | D1: Ранг-RLC | E1: Номер строки, на которой слово стоит в CorST
A2: напишите | B2: 182 | C2: 241.8174 | D2: =RANK(B2,B:B) -> 425 | E2: =MATCH(A2,CorST!A:A,0) -> 10995
A3: озеро | B3: 173 | C3: 229.8594 | D3: =RANK(B3,B:B) -> 452 | E3: =MATCH(A3,CorST!A:A,0) -> 10996
A4: антибиотиков | B4: 156 | C4: 207.27206 | D4: =RANK(B4,B:B) -> 501 | E4: =MATCH(A4,CorST!A:A,0) -> 10997
A5: американцев | B5: 153 | C5: 203.28606 | D5: =RANK(B5,B:B) -> 517 | E5: =MATCH(A5,CorST!A:A,0) -> 10998
A6: байкал | B6: 150 | C6: 199.30006 | D6: =RANK(B6,B:B) -> 530 | E6: =MATCH(A6,CorST!A:A,0) -> 10999
A7: войне | B7: 146 | C7: 193.98539 | D7: =RANK(B7,B:B) -> 549 | E7: =MATCH(A7,CorST!A:A,0) -> 11000
A8: геополитика | B8: 134 | C8: 178.04139 | D8: =RANK(B8,B:B) -> 601 | E8: =MATCH(A8,CorST!A:A,0) -> 11001
A9: американцы | B9: 132 | C9: 175.38405 | D9: =RANK(B9,B:B) -> 606 | E9: =MATCH(A9,CorST!A:A,0) -> 11002
A10: маяковского | B10: 131 | C10: 174.05538 | D10: =RANK(B10,B:B) -> 610 | E10: =MATCH(A10,CorST!A:A,0) -> 11003
A11: советском | B11: 130 | C11: 172.72672 | D11: =RANK(B11,B:B) -> 619 | E11: =MATCH(A11,CorST!A:A,0) -> 11004
A12: озера | B12: 127 | C12: 168.74072 | D12: =RANK(B12,B:B) -> 628 | E12: =MATCH(A12,CorST!A:A,0) -> 11005
A13: пенициллина | B13: 127 | C13: 168.74072 | D13: =RANK(B13,B:B) -> 628 | E13: =MATCH(A13,CorST!A:A,0) -> 11006
... A8127: слово | B8127: 407 | C8127: 540.76749 | D8127: =RANK(B8127,B:B) -> 174 | E8127: =MATCH(A8127,CorST!A:A,0) -> 1

Sheet merge
A1: Слово | B1: IPM-CorST | C1: IPM-CorST
A2: в | B2: 11520.564 | C2: 37993.234
A3: и | B3: 10090.806 | C3: 38334.702
A4: на | B4: 4241.1239 | C4: 13265.412
A5: не | B5: 3791.3953 | C5: 12860.168
A6: с | B6: 3647.5848 | C6: 9178.432
A7: что | B7: 3295.1208 | C7: 16305.402
A8: как | B8: 2374.1562 | C8: 8273.6097
A9: к | B9: 2179.6269 | C9: 4742.0127
A10: а | B10: 1901.6362 | C10: 3449.2197
A11: для | B11: 1814.3227 | C11: 5009.0748
A12: по | B12: 1808.5447 | C12: 4641.034
A13: о | B13: 1576.7787 | C13: 5022.3615
... A61: работы | B61: 349.57492 | C61: 482.30614
A62: предлога | B62: 347.9699
A63: ее | B63: 345.40185 | C63: 987.19962
A64: исследования | B64: 343.47582 | C64: 180.69872
A65: м | B65: 343.47582 | C65: 196.64272
A66: человека | B66: 340.90778 | C66: 1162.5837
A67: языка | B67: 340.90778 | C67: 749.36822
A68: например | B68: 337.05571 | C68: 1194.4717
A69: образом | B69: 334.80867 | C69: 528.80949
A70: чем | B70: 332.56164 | C70: 1353.9117
A71: когда | B71: 332.24063 | C71: 3013.4169
A72: тем | B72: 323.89449 | C72: 976.57029
A73: уже | B73: 321.96846 | C73: 1037.689
A74: этот | B74: 321.64745 | C74: 1195.8003
... A114: люди | B114: 218.6047 | C114: 1909.2946
A115: предлогов | B115: 215.07365
A116: статьи | B116: 213.14761 | C116: 310.90809
A117: п | B117: 211.86359 | C117: 132.86671
A118: после | B118: 211.54259 | C118: 1567.8271
A119: над | B119: 209.29555 | C119: 389.29945
A120: больше | B120: 208.97454 | C120: 1307.4084
A121: несколько | B121: 207.36951 | C121: 572.6555
A122: данной | B122: 204.48047 | C122: 70.419354
A123: была | B123: 203.19644 | C123: 1792.3719
A124: этих | B124: 203.19644 | C124: 615.17285
A125: потому | B125: 202.55443 | C125: 2012.9306
A126: имеет | B126: 202.23343 | C126: 659.01886
A127: года | B127: 200.94941 | C127: 718.80888
... A142: одной | B142: 188.7512 | C142: 495.59281
A143: ст | B143: 188.7512
A144: всегда | B144: 187.78818 | C144: 1020.4163
A145: где | B145: 187.46718 | C145: 1058.9476
A146: информации | B146: 186.82517 | C146: 328.18076
A147: лица | B147: 186.82517 | C147: 54.475349
A148: собой | B148: 186.18316 | C148: 312.23676
A149: суда | B149: 186.18316 | C149: 15.944005
A150: значений | B150: 185.86215
A151: наиболее | B151: 185.86215 | C151: 107.62203
A152: кроме | B152: 184.57813 | C152: 551.39683
A153: себе | B153: 182.6521 | C153: 447.7608
A154: стороны | B154: 179.44204 | C154: 398.60012
A155: е | B155: 178.47902 | C155: 320.20876
A156: свою | B156: 178.47902 | C156: 644.40352
A157: жизнь | B157: 178.15802 | C157: 904.82226
A158: им | B158: 177.83701 | C158: 559.36883
A159: русского | B159: 177.83701 | C159: 503.56481
A160: ему | B160: 177.51601 | C160: 511.53682
A161: данных | B161: 175.91098 | C161: 47.832014
A162: данном | B162: 175.58998 | C162: 46.503347
... A225: сделать | B225: 133.53826 | C225: 361.39744
A226: предлог | B226: 132.57525
A227: существует | B227: 131.93324 | C227: 652.37552
A228: помощью | B228: 131.29123 | C228: 220.55873
A229: поскольку | B229: 130.97022 | C229: 208.60073
A230: два | B230: 130.64921 | C230: 519.50882
A231: ты | B231: 130.0072 | C231: 458.39013
A232: происходит | B232: 129.6862 | C232: 263.07608
A233: разных | B233: 129.6862 | C233: 597.90017
A234: л | B234: 129.36519 | C234: 53.146682
A235: менее | B235: 128.72318 | C235: 320.20876
A236: таких | B236: 128.40218 | C236: 382.65611
A237: процесс | B237: 128.08117 | C237: 309.57942
A238: мой | B238: 127.43916 | C238: 704.19354
... A260: должен | B260: 118.77201 | C260: 382.65611
A261: слово | B261: 118.13 | C261: IPM-RLC
A262: тех | B262: 118.13 | C262: 422.51612
A263: поведения | B263: 117.48799 | C263: 73.076688
A264: термины | B264: 117.48799 | C264: 143.49604
A265: тогда | B265: 117.48799 | C265: 500.90748
A266: влияние | B266: 116.52497 | C266: 333.49543
A267: почему | B267: 116.52497 | C267: 754.68289
A268: группы | B268: 115.88296 | C268: 203.28606
A269: котором | B269: 115.88296 | C269: 304.26476
A270: двух | B270: 115.56196 | C270: 342.7961
A271: раз | B271: 115.56196 | C271: 470.34814
A272: кризис | B272: 115.24095 | C272: 167.41205
A273: друг | B273: 113.63593 | C273: 566.01217
... A298: написан | B298: 106.89481 | C298: 45.17468
A299: сети | B299: 106.2528
A300: мнению | B300: 105.9318 | C300: 358.7401
A301: знания | B301: 105.61079 | C301: 152.79671
A302: среди | B302: 105.28978 | C302: 213.9154
A303: такого | B303: 104.96878 | C303: 150.13938
A304: вреда | B304: 104.64777 | C304: 13.286671
A305: право | B305: 104.64777 | C305: 197.97139
A306: надо | B306: 104.32677 | C306: 866.29092
A307: становится | B307: 104.32677 | C307: 217.9014
...

Sheet Sheet5
A1: напишите | B1: 182 | C1: 241.8174 | D1: =RANK(B1,B:B) -> 1 | E1: =MATCH(A1,CorST!A:A,0) -> 10995
A2: озеро | B2: 173 | C2: 229.8594 | D2: =RANK(B2,B:B) -> 2 | E2: =MATCH(A2,CorST!A:A,0) -> 10996
A3: антибиотиков | B3: 156 | C3: 207.27206 | D3: =RANK(B3,B:B) -> 3 | E3: =MATCH(A3,CorST!A:A,0) -> 10997
A4: американцев | B4: 153 | C4: 203.28606 | D4: =RANK(B4,B:B) -> 4 | E4: =MATCH(A4,CorST!A:A,0) -> 10998
A5: байкал | B5: 150 | C5: 199.30006 | D5: =RANK(B5,B:B) -> 5 | E5: =MATCH(A5,CorST!A:A,0) -> 10999
A6: войне | B6: 146 | C6: 193.98539 | D6: =RANK(B6,B:B) -> 6 | E6: =MATCH(A6,CorST!A:A,0) -> 11000
A7: геополитика | B7: 134 | C7: 178.04139 | D7: =RANK(B7,B:B) -> 7 | E7: =MATCH(A7,CorST!A:A,0) -> 11001
A8: американцы | B8: 132 | C8: 175.38405 | D8: =RANK(B8,B:B) -> 8 | E8: =MATCH(A8,CorST!A:A,0) -> 11002
A9: маяковского | B9: 131 | C9: 174.05538 | D9: =RANK(B9,B:B) -> 9 | E9: =MATCH(A9,CorST!A:A,0) -> 11003
A10: советском | B10: 130 | C10: 172.72672 | D10: =RANK(B10,B:B) -> 10 | E10: =MATCH(A10,CorST!A:A,0) -> 11004
A11: озера | B11: 127 | C11: 168.74072 | D11: =RANK(B11,B:B) -> 11 | E11: =MATCH(A11,CorST!A:A,0) -> 11005
A12: пенициллина | B12: 127 | C12: 168.74072 | D12: =RANK(B12,B:B) -> 11 | E12: =MATCH(A12,CorST!A:A,0) -> 11006
... A3073: японский | B3073: 10 | C3073: 13.286671 | D3073: =RANK(B3073,B:B) -> 2635 | E3073: =MATCH(A3073,CorST!A:A,0) -> #N/A
